convo.py
convo-0.1.0.dist-info/DESCRIPTION.rst
convo-0.1.0.dist-info/METADATA
convo-0.1.0.dist-info/RECORD
convo-0.1.0.dist-info/WHEEL
convo-0.1.0.dist-info/metadata.json
convo-0.1.0.dist-info/top_level.txt
